ghdl/skidbuffer - nodelay.vhd
library ieee;
use ieee.std_logic_1164.all;
use ieee.numeric_std.all;

entity skidbuffer is
  generic (
    DW  : integer := 32;
    OPT_INREG : boolean := True
  );
  port (
    clock     : in std_logic;
    reset_n   : in std_logic;

    s_valid_i : in  std_logic;
    s_last_i  : in  std_logic;
    s_ready_o : out std_logic;
    s_data_i  : in  std_logic_vector(DW - 1 downto 0);

    m_valid_o : out std_logic;
    m_last_o  : out std_logic;
    m_ready_i : in  std_logic;
    m_data_o  : out std_logic_vector(DW - 1 downto 0)
  );
end skidbuffer;

architecture arch_imp of skidbuffer is
  -- input signals (registered depending on OPT_INREG)
  signal reg_data  : std_logic_vector(DW-1 downto 0);
  signal reg_last  : std_logic;
  signal reg_valid : std_logic;
  signal reg_ready : std_logic;

  -- skid buffer signals from Slave to Master direction
  signal skd_data  : std_logic_vector(DW-1 downto 0);
  signal skd_last  : std_logic;

  -- output signals
  signal out_data  : std_logic_vector(DW-1 downto 0);
  signal out_last  : std_logic;
  signal out_ready : std_logic;

begin
  -- I/O connections assignments
  m_valid_o <= reg_valid;
  reg_valid <= s_valid_i;

  out_ready <= reg_ready;
  s_ready_o <= out_ready;

  m_data_o  <= out_data;
  m_last_o  <= out_last;

  -- combinatorial multiplexers
  -- "output" = "input" when ready==1, otherwise use "buffer content"
  out_data <= s_data_i when (reg_ready = '1') else skd_data;
  out_last <= s_last_i when (reg_ready = '1') else skd_last;

  p_reg_ready : process(clock)
  begin
    if rising_edge(clock) then 
      if reset_n = '0' then
        reg_ready <= '0';
      else
        reg_ready <= m_ready_i;
      end if;
    end if;
  end process;

  -- skid buffer looping output back into register
  p_skid_buf : process (clock)
  begin
    if rising_edge(clock) then 
      if reset_n = '0' then
        skd_data <= (others => '0');
        skd_last <= '0';
      else
        if reg_ready = '1' then
          skd_data <= s_data_i;
          skd_last <= s_last_i;
        else
          skd_data <= skd_data;
          skd_last <= skd_last;
        end if;
      end if;
    end if;
  end process;

end arch_imp;

ghdl/tb_skid.vhd
----------------------------------------------------------------------------------
-- Company: 
-- Engineer: 
-- 
-- Create Date: 03/22/2023 09:03:36 AM
-- Design Name: 
-- Module Name: tb_skid - bh
-- Project Name: 
-- Target Devices: 
-- Tool Versions: 
-- Description: 
-- 
-- Dependencies: 
-- 
-- Revision:
-- Revision 0.01 - File Created
-- Additional Comments:
-- 
----------------------------------------------------------------------------------


library ieee;
use ieee.std_logic_1164.all;
use ieee.numeric_std.all;

-- Uncomment the following library declaration if using
-- arithmetic functions with Signed or Unsigned values
--use IEEE.NUMERIC_STD.ALL;

-- Uncomment the following library declaration if instantiating
-- any Xilinx leaf cells in this code.
--library UNISIM;
--use UNISIM.VComponents.all;

entity tb_skid is
  generic
  (
    DW        : natural := 8;
    OPT_INREG : boolean := True
  );
end tb_skid;

architecture bh of tb_skid is
  -- component declaration
  component skidbuffer is
  generic (
    DW         : natural;
    OPT_INREG : boolean);
    port (
       clock     : in  std_logic;
       reset_n   : in  std_logic;

       s_valid_i : in  std_logic;
       s_last_i  : in  std_logic;
       s_ready_o : out std_logic;
       s_data_i  : in  std_logic_vector(DW - 1 downto 0);

       m_valid_o : out std_logic;
       m_last_o  : out std_logic;
       m_ready_i : in  std_logic;
       m_data_o  : out std_logic_vector(DW - 1 downto 0));
  end component;
  
  constant CLK_PERIOD: TIME := 5 ns;

  signal sim_valid_data  : std_logic := '0';
  signal sim_ready_data  : std_logic := '1';
  signal sim_data        : std_logic_vector(DW-1 downto 0);

  signal s_axis_tvalid : std_logic := '0';
  signal s_axis_tdata  : std_logic_vector(DW-1 downto 0);
  signal s_axis_tlast  : std_logic;
  signal s_axis_tready : std_logic;

  signal m_axis_tvalid : std_logic;
  signal m_axis_tdata  : std_logic_vector(DW-1 downto 0);
  signal m_axis_tlast  : std_logic;
  signal m_axis_tready : std_logic := '0';

  signal clk   : std_logic;
  signal rst_n : std_logic;

  signal clk_count : std_logic_vector(7 downto 0) := (others => '0');
begin

  -- generate clk signal
  p_clk_gen : process
  begin
   clk <= '1';
   wait for (CLK_PERIOD / 2);
   clk <= '0';
   wait for (CLK_PERIOD / 2);
   clk_count <= std_logic_vector(unsigned(clk_count) + 1);
  end process;

  -- generate initial reset
  p_reset_gen : process
  begin 
    rst_n <= '0';
    wait until rising_edge(clk);
    wait for (CLK_PERIOD / 4);
    rst_n <= '1';
    wait;
  end process;

  -- generate ready signal
  p_stimuli_tready : process(clk)
  begin
    if rising_edge(clk) then
      if rst_n = '0' then
        m_axis_tready <= '1';
      else
        m_axis_tready <= sim_ready_data;
        if unsigned(clk_count) = 2 then
          sim_ready_data <= '1';
        end if;
        if unsigned(clk_count) = 7 then
          sim_ready_data <= '0';
        end if;
        if unsigned(clk_count) = 8 then
          sim_ready_data <= '1';
        end if;
        if unsigned(clk_count) = 11 then
          sim_ready_data <= '0';
        end if;
        if unsigned(clk_count) = 13 then
          sim_ready_data <= '1';
        end if;
        if unsigned(clk_count) = 14 then
          sim_ready_data <= '0';
        end if;
        if unsigned(clk_count) = 15 then
          sim_ready_data <= '1';
        end if;
      end if;
    end if;
  end process;

  -- generate valid signal
  p_stimuli_tvalid : process(clk)
  begin
    if rising_edge(clk) then
      if rst_n = '0' then
        sim_valid_data <= '0';
      else
        if unsigned(clk_count) = 2 then
          sim_valid_data <= '1';
        end if;
        if unsigned(clk_count) = 18 then
          sim_valid_data <= '0';
        end if;
        if unsigned(clk_count) = 21 then
          sim_valid_data <= '1';
        end if;
        if unsigned(clk_count) = 23 then
          sim_valid_data <= '0';
        end if;
        if unsigned(clk_count) = 24 then
          sim_valid_data <= '1';
        end if;
        if unsigned(clk_count) = 26 then
          sim_valid_data <= '0';
        end if;
      end if;
    end if;
  end process;

    -- TODO: this is a bug. m_axis is a stimulated signal and not read from the DUT
    -- why is this if-statement delayed by 1 clk? it should read from s_axis_tready instead
  -- generate counter data when successfully acknowledged by slave
  p_stimuli_tdata : process(clk)
  begin
    if rising_edge(clk) then
      if rst_n = '0' then
        s_axis_tdata <= (others => '0');
        sim_data <= (others => '0');
        s_axis_tlast <= '0';
      else
        if sim_valid_data = '1' then    -- VALID can be controlled
          if s_axis_tready = '1' then   -- READY can be controlled
            if unsigned(s_axis_tdata) = 4 then
              s_axis_tdata(DW-1 downto 1) <= (others => '0');
              s_axis_tdata(0) <= '1';
              sim_data(DW-1 downto 1) <= (others => '0');
              sim_data(0) <= '1';
              s_axis_tlast <= '1';
            else
              if (unsigned(sim_data) > unsigned(s_axis_tdata)) and (unsigned(sim_data) < 4) then
                s_axis_tdata <= std_logic_vector(unsigned(sim_data) + 1);
              else
                s_axis_tdata <= std_logic_vector(unsigned(s_axis_tdata) + 1);
              end if;
              
              if unsigned(sim_data) = 4 then
                sim_data(DW-1 downto 1) <= (others => '0');
                sim_data(0) <= '1';
              else
                sim_data <= std_logic_vector(unsigned(sim_data) + 1);
              end if;
              s_axis_tlast <= '0';
            end if;
          else
            s_axis_tdata <= s_axis_tdata;
            sim_data <= sim_data;
          end if;
          s_axis_tvalid <= '1';
        else 
          s_axis_tvalid <= '0';
          s_axis_tlast <= '0';
          s_axis_tdata <= (others => '0');
          sim_data <= sim_data;
        end if;
      end if;
    end if;
  end process;

  skidbuffer_inst : skidbuffer
  generic map (
      DW         => DW,
      OPT_INREG  => OPT_INREG
  )
  port map (
    clock     => clk,
    reset_n   => rst_n,

    s_valid_i => s_axis_tvalid,
    s_last_i  => s_axis_tlast,
    s_ready_o => s_axis_tready,
    s_data_i  => s_axis_tdata,

    m_valid_o => m_axis_tvalid,
    m_last_o  => m_axis_tlast,
    m_ready_i => m_axis_tready,
    m_data_o  => m_axis_tdata
  );

end bh;

ghdl/wave.vcd
$date
  Wed Apr 19 17:47:28 2023
$end
$version
  GHDL v0
$end
$timescale
  1 fs
$end
$scope module standard $end
$upscope $end
$scope module std_logic_1164 $end
$upscope $end
$scope module numeric_std $end
$upscope $end
$scope module tb_skid $end
$var reg 1 ! sim_valid_data $end
$var reg 1 " sim_ready_data $end
$var reg 8 # sim_data[7:0] $end
$var reg 1 $ s_axis_tvalid $end
$var reg 8 % s_axis_tdata[7:0] $end
$var reg 1 & s_axis_tlast $end
$var reg 1 ' s_axis_tready $end
$var reg 1 ( m_axis_tvalid $end
$var reg 8 ) m_axis_tdata[7:0] $end
$var reg 1 * m_axis_tlast $end
$var reg 1 + m_axis_tready $end
$var reg 1 , clk $end
$var reg 1 - rst_n $end
$var reg 8 . clk_count[7:0] $end
$scope module skidbuffer_inst $end
$var reg 1 / clock $end
$var reg 1 0 reset_n $end
$var reg 1 1 s_valid_i $end
$var reg 1 2 s_last_i $end
$var reg 1 3 s_ready_o $end
$var reg 8 4 s_data_i[7:0] $end
$var reg 1 5 m_valid_o $end
$var reg 1 6 m_last_o $end
$var reg 1 7 m_ready_i $end
$var reg 8 8 m_data_o[7:0] $end
$var reg 8 9 reg_data[7:0] $end
$var reg 1 : reg_last $end
$var reg 1 ; reg_valid $end
$var reg 1 < reg_ready $end
$var reg 8 = skd_data[7:0] $end
$var reg 1 > skd_last $end
$var reg 8 ? out_data[7:0] $end
$var reg 1 @ out_last $end
$var reg 1 A out_ready $end
$scope module gen_input_register $end
$upscope $end
$upscope $end
$upscope $end
$enddefinitions $end
#0
0!
1"
bUUUUUUUU #
0$
bUUUUUUUU %
U&
U'
U(
bUUUUUUUU )
U*
0+
1,
0-
b00000000 .
1/
00
01
U2
U3
bUUUUUUUU 4
U5
U6
07
bUUUUUUUU 8
bUUUUUUUU 9
U:
U;
U<
bUUUUUUUU =
U>
bUUUUUUUU ?
U@
UA
#2500000
0,
0/
#5000000
b00000000 #
b00000000 %
0&
0'
0(
b00000000 )
0*
1+
1,
b00000001 .
1/
02
03
b00000000 4
05
06
17
b00000000 8
b00000000 9
0:
0;
0<
b00000000 =
0>
b00000000 ?
0@
0A
#6250000
1-
10
#7500000
0,
0/
#10000000
1!
1'
1,
b00000010 .
1/
13
1<
1A
#12500000
0,
0/
#15000000
b00000001 #
1$
b00000001 %
1,
b00000011 .
1/
11
b00000001 4
#17500000
0,
0/
#20000000
b00000010 #
b00000010 %
1(
b00000001 )
1,
b00000100 .
1/
b00000010 4
15
b00000001 8
b00000001 9
1;
b00000001 ?
#22500000
0,
0/
#25000000
b00000011 #
b00000011 %
b00000010 )
1,
b00000101 .
1/
b00000011 4
b00000010 8
b00000010 9
b00000001 =
b00000010 ?
#27500000
0,
0/
#30000000
b00000100 #
b00000100 %
b00000011 )
1,
b00000110 .
1/
b00000100 4
b00000011 8
b00000011 9
b00000010 =
b00000011 ?
#32500000
0,
0/
#35000000
0"
b00000001 #
b00000001 %
1&
b00000100 )
1,
b00000111 .
1/
12
b00000001 4
b00000100 8
b00000100 9
b00000011 =
b00000100 ?
#37500000
0,
0/
#40000000
1"
b00000010 #
b00000010 %
0&
b00000001 )
1*
0+
1,
b00001000 .
1/
02
b00000010 4
16
07
b00000001 8
b00000001 9
1:
b00000100 =
b00000001 ?
1@
#42500000
0,
0/
#45000000
b00000011 #
b00000011 %
0'
1+
1,
b00001001 .
1/
03
b00000011 4
17
b00000010 9
0:
0<
b00000001 =
1>
0A
#47500000
0,
0/
#50000000
1'
b00000010 )
0*
1,
b00001010 .
1/
13
06
b00000010 8
1<
b00000010 ?
0@
1A
#52500000
0,
0/
#55000000
0"
b00000100 #
b00000100 %
b00000011 )
1,
b00001011 .
1/
b00000100 4
b00000011 8
b00000011 9
b00000010 =
0>
b00000011 ?
#57500000
0,
0/
#60000000
b00000001 #
b00000001 %
1&
b00000100 )
0+
1,
b00001100 .
1/
12
b00000001 4
07
b00000100 8
b00000100 9
b00000011 =
b00000100 ?
#62500000
0,
0/
#65000000
1"
b00000010 #
b00000010 %
0&
0'
1,
b00001101 .
1/
02
03
b00000010 4
b00000001 9
1:
0<
b00000100 =
0A
#67500000
0,
0/
#70000000
0"
1+
1,
b00001110 .
1/
17
#72500000
0,
0/
#75000000
1"
1'
b00000001 )
1*
0+
1,
b00001111 .
1/
13
16
07
b00000001 8
1<
b00000001 ?
1@
1A
#77500000
0,
0/
#80000000
b00000011 #
b00000011 %
0'
1+
1,
b00010000 .
1/
03
b00000011 4
17
b00000010 9
0:
0<
b00000001 =
1>
0A
#82500000
0,
0/
#85000000
1'
b00000010 )
0*
1,
b00010001 .
1/
13
06
b00000010 8
1<
b00000010 ?
0@
1A
#87500000
0,
0/
#90000000
0!
b00000100 #
b00000100 %
b00000011 )
1,
b00010010 .
1/
b00000100 4
b00000011 8
b00000011 9
b00000010 =
0>
b00000011 ?
#92500000
0,
0/
#95000000
0$
b00000000 %
b00000100 )
1,
b00010011 .
1/
01
b00000000 4
b00000100 8
b00000100 9
b00000011 =
b00000100 ?
#97500000
0,
0/
#100000000
0(
b00000000 )
1,
b00010100 .
1/
05
b00000000 8
b00000000 9
0;
b00000100 =
b00000000 ?
#102500000
0,
0/
#105000000
1!
1,
b00010101 .
1/
b00000000 =
#107500000
0,
0/
#110000000
b00000001 #
1$
b00000001 %
1,
b00010110 .
1/
11
b00000001 4
#112500000
0,
0/
#115000000
0!
b00000010 #
b00000010 %
1(
b00000001 )
1,
b00010111 .
1/
b00000010 4
15
b00000001 8
b00000001 9
1;
b00000001 ?
#117500000
0,
0/
#120000000
1!
0$
b00000000 %
b00000010 )
1,
b00011000 .
1/
01
b00000000 4
b00000010 8
b00000010 9
b00000001 =
b00000010 ?
#122500000
0,
0/
#125000000
b00000011 #
1$
b00000011 %
0(
b00000000 )
1,
b00011001 .
1/
11
b00000011 4
05
b00000000 8
b00000000 9
0;
b00000010 =
b00000000 ?
#127500000
0,
0/
#130000000
0!
b00000100 #
b00000100 %
1(
b00000011 )
1,
b00011010 .
1/
b00000100 4
15
b00000011 8
b00000011 9
1;
b00000000 =
b00000011 ?
#132500000
0,
0/
#135000000
0$
b00000000 %
b00000100 )
1,
b00011011 .
1/
01
b00000000 4
b00000100 8
b00000100 9
b00000011 =
b00000100 ?
#137500000
0,
0/
#140000000
0(
b00000000 )
1,
b00011100 .
1/
05
b00000000 8
b00000000 9
0;
b00000100 =
b00000000 ?
#142500000
0,
0/
#145000000
1,
b00011101 .
1/
b00000000 =
#147500000
0,
0/
#150000000
1,
b00011110 .
1/
#152500000
0,
0/
#155000000
1,
b00011111 .
1/
#157500000
0,
0/
#160000000
1,
b00100000 .
1/
#162500000
0,
0/
#165000000
1,
b00100001 .
1/
#167500000
0,
0/
#170000000
1,
b00100010 .
1/
#172500000
0,
0/
#175000000
1,
b00100011 .
1/
#177500000
0,
0/
#180000000
1,
b00100100 .
1/
#182500000
0,
0/
#185000000
1,
b00100101 .
1/
#187500000
0,
0/
#190000000
1,
b00100110 .
1/
#192500000
0,
0/
#195000000
1,
b00100111 .
1/
#197500000
0,
0/
#200000000
1,
b00101000 .
1/
#202500000
0,
0/
#205000000
1,
b00101001 .
1/
#207500000
0,
0/
#210000000
1,
b00101010 .
1/
#212500000
0,
0/
#215000000
1,
b00101011 .
1/
#217500000
0,
0/
#220000000
1,
b00101100 .
1/
#222500000
0,
0/
#225000000
1,
b00101101 .
1/
#227500000
0,
0/
#230000000
1,
b00101110 .
1/
#232500000
0,
0/
#235000000
1,
b00101111 .
1/
#237500000
0,
0/
#240000000
1,
b00110000 .
1/
#242500000
0,
0/
#245000000
1,
b00110001 .
1/
#247500000
0,
0/
#250000000
1,
b00110010 .
1/
#252500000
0,
0/
#255000000
1,
b00110011 .
1/
#257500000
0,
0/
#260000000
1,
b00110100 .
1/
#262500000
0,
0/
#265000000
1,
b00110101 .
1/
#267500000
0,
0/
#270000000
1,
b00110110 .
1/
#272500000
0,
0/
#275000000
1,
b00110111 .
1/
#277500000
0,
0/
#280000000
1,
b00111000 .
1/
#282500000
0,
0/
#285000000
1,
b00111001 .
1/
#287500000
0,
0/
#290000000
1,
b00111010 .
1/
#292500000
0,
0/
#295000000
1,
b00111011 .
1/
#297500000
0,
0/
#300000000
1,
b00111100 .
1/
#302500000
0,
0/
#305000000
1,
b00111101 .
1/
#307500000
0,
0/
#310000000
1,
b00111110 .
1/
#312500000
0,
0/
#315000000
1,
b00111111 .
1/
#317500000
0,
0/
#320000000
1,
b01000000 .
1/
#322500000
0,
0/
#325000000
1,
b01000001 .
1/
#327500000
0,
0/
#330000000
1,
b01000010 .
1/
#332500000
0,
0/
#335000000
1,
b01000011 .
1/
#337500000
0,
0/
#340000000
1,
b01000100 .
1/
#342500000
0,
0/
#345000000
1,
b01000101 .
1/
#347500000
0,
0/
#350000000
1,
b01000110 .
1/
#352500000
0,
0/
#355000000
1,
b01000111 .
1/
#357500000
0,
0/
#360000000
1,
b01001000 .
1/
#362500000
0,
0/
#365000000
1,
b01001001 .
1/
#367500000
0,
0/
#370000000
1,
b01001010 .
1/
#372500000
0,
0/
#375000000
1,
b01001011 .
1/
#377500000
0,
0/
#380000000
1,
b01001100 .
1/
#382500000
0,
0/
#385000000
1,
b01001101 .
1/
#387500000
0,
0/
#390000000
1,
b01001110 .
1/
#392500000
0,
0/
#395000000
1,
b01001111 .
1/
#397500000
0,
0/
#400000000
1,
b01010000 .
1/
#402500000
0,
0/
#405000000
1,
b01010001 .
1/
#407500000
0,
0/
#410000000
1,
b01010010 .
1/
#412500000
0,
0/
#415000000
1,
b01010011 .
1/
#417500000
0,
0/
#420000000
1,
b01010100 .
1/
#422500000
0,
0/
#425000000
1,
b01010101 .
1/
#427500000
0,
0/
#430000000
1,
b01010110 .
1/
#432500000
0,
0/
#435000000
1,
b01010111 .
1/
#437500000
0,
0/
#440000000
1,
b01011000 .
1/
#442500000
0,
0/
#445000000
1,
b01011001 .
1/
#447500000
0,
0/
#450000000
1,
b01011010 .
1/
#452500000
0,
0/
#455000000
1,
b01011011 .
1/
#457500000
0,
0/
#460000000
1,
b01011100 .
1/
#462500000
0,
0/
#465000000
1,
b01011101 .
1/
#467500000
0,
0/
#470000000
1,
b01011110 .
1/
#472500000
0,
0/
#475000000
1,
b01011111 .
1/
#477500000
0,
0/
#480000000
1,
b01100000 .
1/
#482500000
0,
0/
#485000000
1,
b01100001 .
1/
#487500000
0,
0/
#490000000
1,
b01100010 .
1/
#492500000
0,
0/
#495000000
1,
b01100011 .
1/
#497500000
0,
0/
#500000000
1,
b01100100 .
1/
#502500000
0,
0/
#505000000
1,
b01100101 .
1/
#507500000
0,
0/
#510000000
1,
b01100110 .
1/
#512500000
0,
0/
#515000000
1,
b01100111 .
1/
#517500000
0,
0/
#520000000
1,
b01101000 .
1/
#522500000
0,
0/
#525000000
1,
b01101001 .
1/
#527500000
0,
0/
#530000000
1,
b01101010 .
1/
#532500000
0,
0/
#535000000
1,
b01101011 .
1/
#537500000
0,
0/
#540000000
1,
b01101100 .
1/
#542500000
0,
0/
#545000000
1,
b01101101 .
1/
#547500000
0,
0/
#550000000
1,
b01101110 .
1/
#552500000
0,
0/
#555000000
1,
b01101111 .
1/
#557500000
0,
0/
#560000000
1,
b01110000 .
1/
#562500000
0,
0/
#565000000
1,
b01110001 .
1/
#567500000
0,
0/
#570000000
1,
b01110010 .
1/
#572500000
0,
0/
#575000000
1,
b01110011 .
1/
#577500000
0,
0/
#580000000
1,
b01110100 .
1/
#582500000
0,
0/
#585000000
1,
b01110101 .
1/
#587500000
0,
0/
#590000000
1,
b01110110 .
1/
#592500000
0,
0/
#595000000
1,
b01110111 .
1/
#597500000
0,
0/
#600000000
1,
b01111000 .
1/
#602500000
0,
0/
#605000000
1,
b01111001 .
1/
#607500000
0,
0/
#610000000
1,
b01111010 .
1/
#612500000
0,
0/
#615000000
1,
b01111011 .
1/
#617500000
0,
0/
#620000000
1,
b01111100 .
1/
#622500000
0,
0/
#625000000
1,
b01111101 .
1/
#627500000
0,
0/
#630000000
1,
b01111110 .
1/
#632500000
0,
0/
#635000000
1,
b01111111 .
1/
#637500000
0,
0/
#640000000
1,
b10000000 .
1/
#642500000
0,
0/
#645000000
1,
b10000001 .
1/
#647500000
0,
0/
#650000000
1,
b10000010 .
1/
#652500000
0,
0/
#655000000
1,
b10000011 .
1/
#657500000
0,
0/
#660000000
1,
b10000100 .
1/
#662500000
0,
0/
#665000000
1,
b10000101 .
1/
#667500000
0,
0/
#670000000
1,
b10000110 .
1/
#672500000
0,
0/
#675000000
1,
b10000111 .
1/
#677500000
0,
0/
#680000000
1,
b10001000 .
1/
#682500000
0,
0/
#685000000
1,
b10001001 .
1/
#687500000
0,
0/
#690000000
1,
b10001010 .
1/
#692500000
0,
0/
#695000000
1,
b10001011 .
1/
#697500000
0,
0/
#700000000
1,
b10001100 .
1/
#702500000
0,
0/
#705000000
1,
b10001101 .
1/
#707500000
0,
0/
#710000000
1,
b10001110 .
1/
#712500000
0,
0/
#715000000
1,
b10001111 .
1/
#717500000
0,
0/
#720000000
1,
b10010000 .
1/
#722500000
0,
0/
#725000000
1,
b10010001 .
1/
#727500000
0,
0/
#730000000
1,
b10010010 .
1/
#732500000
0,
0/
#735000000
1,
b10010011 .
1/
#737500000
0,
0/
#740000000
1,
b10010100 .
1/
#742500000
0,
0/
#745000000
1,
b10010101 .
1/
#747500000
0,
0/
#750000000
1,
b10010110 .
1/
#752500000
0,
0/
#755000000
1,
b10010111 .
1/
#757500000
0,
0/
#760000000
1,
b10011000 .
1/
#762500000
0,
0/
#765000000
1,
b10011001 .
1/
#767500000
0,
0/
#770000000
1,
b10011010 .
1/
#772500000
0,
0/
#775000000
1,
b10011011 .
1/
#777500000
0,
0/
#780000000
1,
b10011100 .
1/
#782500000
0,
0/
#785000000
1,
b10011101 .
1/
#787500000
0,
0/
#790000000
1,
b10011110 .
1/
#792500000
0,
0/
#795000000
1,
b10011111 .
1/
#797500000
0,
0/
#800000000
1,
b10100000 .
1/
#802500000
0,
0/
#805000000
1,
b10100001 .
1/
#807500000
0,
0/
#810000000
1,
b10100010 .
1/
#812500000
0,
0/
#815000000
1,
b10100011 .
1/
#817500000
0,
0/
#820000000
1,
b10100100 .
1/
#822500000
0,
0/
#825000000
1,
b10100101 .
1/
#827500000
0,
0/
#830000000
1,
b10100110 .
1/
#832500000
0,
0/
#835000000
1,
b10100111 .
1/
#837500000
0,
0/
#840000000
1,
b10101000 .
1/
#842500000
0,
0/
#845000000
1,
b10101001 .
1/
#847500000
0,
0/
#850000000
1,
b10101010 .
1/
#852500000
0,
0/
#855000000
1,
b10101011 .
1/
#857500000
0,
0/
#860000000
1,
b10101100 .
1/
#862500000
0,
0/
#865000000
1,
b10101101 .
1/
#867500000
0,
0/
#870000000
1,
b10101110 .
1/
#872500000
0,
0/
#875000000
1,
b10101111 .
1/
#877500000
0,
0/
#880000000
1,
b10110000 .
1/
#882500000
0,
0/
#885000000
1,
b10110001 .
1/
#887500000
0,
0/
#890000000
1,
b10110010 .
1/
#892500000
0,
0/
#895000000
1,
b10110011 .
1/
#897500000
0,
0/
#900000000
1,
b10110100 .
1/
#902500000
0,
0/
#905000000
1,
b10110101 .
1/
#907500000
0,
0/
#910000000
1,
b10110110 .
1/
#912500000
0,
0/
#915000000
1,
b10110111 .
1/
#917500000
0,
0/
#920000000
1,
b10111000 .
1/
#922500000
0,
0/
#925000000
1,
b10111001 .
1/
#927500000
0,
0/
#930000000
1,
b10111010 .
1/
#932500000
0,
0/
#935000000
1,
b10111011 .
1/
#937500000
0,
0/
#940000000
1,
b10111100 .
1/
#942500000
0,
0/
#945000000
1,
b10111101 .
1/
#947500000
0,
0/
#950000000
1,
b10111110 .
1/
#952500000
0,
0/
#955000000
1,
b10111111 .
1/
#957500000
0,
0/
#960000000
1,
b11000000 .
1/
#962500000
0,
0/
#965000000
1,
b11000001 .
1/
#967500000
0,
0/
#970000000
1,
b11000010 .
1/
#972500000
0,
0/
#975000000
1,
b11000011 .
1/
#977500000
0,
0/
#980000000
1,
b11000100 .
1/
#982500000
0,
0/
#985000000
1,
b11000101 .
1/
#987500000
0,
0/
#990000000
1,
b11000110 .
1/
#992500000
0,
0/
#995000000
1,
b11000111 .
1/
#997500000
0,
0/
#1000000000
1,
b11001000 .
1/
